sqlite_dns/__init__.py
sqlite_dns/version.py
sqlite_dns/lib/sqlite_dns.so
sqlite_dns-0.1.2.dist-info/METADATA
sqlite_dns-0.1.2.dist-info/WHEEL
sqlite_dns-0.1.2.dist-info/top_level.txt
sqlite_dns-0.1.2.dist-info/RECORD
