Metadata-Version: 2.1
Name: sqlite-dns
Version: 0.1.2
Summary: A sqlite3 extension that allows you to query DNS using SQL
Home-page: https://github.com/riyaz-ali/dns.sql
Author: Riyaz Ali
License: MIT License
Project-URL: Issues, https://github.com/riyaz-ali/dns.sql/issues
Project-URL: Changelog, https://github.com/riyaz-ali/dns.sql/releases
Requires-Python: >=3.7
